{
  "heaven_gilded_bookcase": "116828384640255",
  "heaven_golden_throne": "123245497958234",
  "hell_infernal_fountain": "88910985784852",
  "hell_infernal_throne": "140167686562423",
  "hell_infernal_throne_flat": "106807792456589",
  "heaven_archive": "128611924897803",
  "heaven_compass_banner": "82245370112313",
  "heaven_diamond_altar": "111505499845921",
  "heaven_flamecrest_shield": "108671572277078",
  "heaven_golden_codex": "102961399322216",
  "heaven_golden_guardian": "118224391576229",
  "heaven_ivory_throne": "72211882875371",
  "heaven_marble_throne": "73086280079401",
  "heaven_star_fountain": "136412156431643",
  "hell_gate_of_damned": "104034775847710",
  "hell_infernal_archive": "95760597473450",
  "hell_infernal_crest": "129603133429738",
  "hell_skull_banner": "106866354186394",
  "hell_skull_sconce": "128244126555810",
  "hell_skull_lantern": "92353414798210"
}